boards/__init__.py
boards/main.py
boards-0.3.1.dist-info/entry_points.txt
boards-0.3.1.dist-info/WHEEL
boards-0.3.1.dist-info/METADATA
boards-0.3.1.dist-info/RECORD
