Metadata-Version: 2.1
Name: boards
Version: 0.3.1
Summary: Recursive kanban tool in the command line
Requires-Python: >=3.6
Requires-Dist: send2trash
Requires-Dist: rich
Requires-Dist: tomlkit
Requires-Dist: typer
